tester_flask/__init__.py
tester_flask-1.2.dist-info/LICENSE
tester_flask-1.2.dist-info/METADATA
tester_flask-1.2.dist-info/WHEEL
tester_flask-1.2.dist-info/top_level.txt
tester_flask-1.2.dist-info/RECORD
