Metadata-Version: 2.1
Name: tester_flask
Version: 1.2
Summary: Class for autotests flask python apps
Home-page: https://github.com/vb64/test.helper.flask
Author: Vitaly Bogomolov
Author-email: mail@vitaly-bogomolov.ru
Project-URL: Bug Tracker, https://github.com/vb64/test.helper.flask/issues
Classifier: Programming Language :: Python
Classifier: License :: OSI Approved :: MIT License
Classifier: Operating System :: OS Independent
License-File: LICENSE
